rain/__init__.py
rain/authenticate.py
rain/cli.py
rain/client.py
rain/defaults.py
rain/fetch.py
rain/generate.py
rain/get_api.py
rain/packaging.py
rain/plugins.py
rain/register.py
rain/server.py
rain/transport.py
rain/trigger.py
rain/validate.py
rain/version.py
pyrain-0.5.1.dist-info/LICENSE
pyrain-0.5.1.dist-info/METADATA
pyrain-0.5.1.dist-info/WHEEL
pyrain-0.5.1.dist-info/entry_points.txt
pyrain-0.5.1.dist-info/top_level.txt
pyrain-0.5.1.dist-info/RECORD
