Metadata-Version: 2.1
Name: pyrain
Version: 0.5.1
Summary: Communication network linking research infrastructure using TCP/IP json messages
Author-email: Calum Lonie <callon-2@student.ltu.se>, Daniel Kastinen <daniel.kastinen@irf.se>
Maintainer-email: Daniel Kastinen <daniel.kastinen@irf.se>
License: GNU GENERAL PUBLIC LICENSE
Project-URL: Documentation, https://danielk.developer.irf.se/rain/
Project-URL: Repository, https://github.com/danielk333/rain
Project-URL: Homepage, https://github.com/danielk333/rain
Project-URL: Issues, https://github.com/danielk333/rain/issues
Classifier: Intended Audience :: Science/Research
Classifier: Programming Language :: Python :: 3
Classifier: Topic :: Scientific/Engineering :: Physics
Requires-Python: >=3.5
License-File: LICENSE
Requires-Dist: pyzmq
Requires-Dist: jsonschema
Provides-Extra: develop
Requires-Dist: pytest ; extra == 'develop'
Requires-Dist: flake8 ; extra == 'develop'
Requires-Dist: wheel ; extra == 'develop'
Requires-Dist: build ; extra == 'develop'
Requires-Dist: twine ; extra == 'develop'
Requires-Dist: pre-commit ; extra == 'develop'
Requires-Dist: black ; extra == 'develop'
Requires-Dist: mkdocs-material ; extra == 'develop'
Requires-Dist: mkdocstrings[python] ; extra == 'develop'
